ioant/__init__.py
ioant/proto/__init__.py
ioant/proto/proto.py
ioant/proto/messages/messages.options
ioant/proto/messages/messages.proto
ioant/proto/messages/generators/include/google/protobuf/any.proto
ioant/proto/messages/generators/include/google/protobuf/api.proto
ioant/proto/messages/generators/include/google/protobuf/descriptor.proto
ioant/proto/messages/generators/include/google/protobuf/duration.proto
ioant/proto/messages/generators/include/google/protobuf/empty.proto
ioant/proto/messages/generators/include/google/protobuf/field_mask.proto
ioant/proto/messages/generators/include/google/protobuf/source_context.proto
ioant/proto/messages/generators/include/google/protobuf/struct.proto
ioant/proto/messages/generators/include/google/protobuf/timestamp.proto
ioant/proto/messages/generators/include/google/protobuf/type.proto
ioant/proto/messages/generators/include/google/protobuf/wrappers.proto
ioant/proto/messages/generators/include/google/protobuf/compiler/plugin.proto
ioant/proto/messages/generators/nanopb/nanopb_generator.py
ioant/proto/messages/generators/nanopb/protoc-gen-nanopb
ioant/proto/messages/generators/nanopb/proto/__init__.py
ioant/proto/messages/generators/nanopb/proto/nanopb.proto
ioant/proto/messages/generators/nanopb/proto/nanopb_pb2.py
ioant/proto/messages/generators/nanopb/proto/plugin.proto
ioant/proto/messages/generators/nanopb/proto/plugin_pb2.py
ioant/proto/messages/generators/nanopb/proto/google/protobuf/descriptor.proto
ioant/proto/templates/condition.template.py
ioant/proto/templates/message_cases.template.cpp
ioant/proto/templates/message_class.template.cpp
ioant/proto/templates/message_class.template.h
ioant/proto/templates/proto_io.template.cpp
ioant/proto/templates/proto_io.template.h
ioant/proto/templates/proto_io.template.py
ioant/sdk/__init__.py
ioant/sdk/sdk.py
ioant/tests/__init__.py
ioant/tests/messages_pb2.py
ioant/tests/proto_io.py
ioant/tests/test_sdk.py
ioant/utils/__init__.py
ioant-0.3.7.dist-info/DESCRIPTION.rst
ioant-0.3.7.dist-info/METADATA
ioant-0.3.7.dist-info/RECORD
ioant-0.3.7.dist-info/WHEEL
ioant-0.3.7.dist-info/metadata.json
ioant-0.3.7.dist-info/top_level.txt
