Metadata-Version: 2.0
Name: ioant
Version: 0.3.7
Summary: This is the official IOAnt package. Contains the SDK, Proto-generator and utils
Home-page: http://ioant.com
Author: Adam Saxen
Author-email: adam@asaxen.com
License: MIT
Platform: UNKNOWN
Requires-Dist: mock (>=2.0.0)
Requires-Dist: nose (>=1.3.7)
Requires-Dist: paho-mqtt (>=1.2)
Requires-Dist: protobuf (>=3.0.0)
